rachel/__init__.py
rachel/fields.py
rachel/routers.py
rachel/serializers.py
rachel/test.py
rachel/views.py
rachel/exceptions/__init__.py
rachel/exceptions/bases.py
rachel/exceptions/system.py
rachel/utils/__init__.py
rachel/utils/decrators.py
rachel/utils/q.py
rachel-0.1.0.dist-info/LICENSE
rachel-0.1.0.dist-info/METADATA
rachel-0.1.0.dist-info/WHEEL
rachel-0.1.0.dist-info/top_level.txt
rachel-0.1.0.dist-info/RECORD
