Metadata-Version: 2.1
Name: rachel
Version: 0.1.0
Summary: UNKNOWN
Home-page: UNKNOWN
Author: Ethan
Author-email: ismewen@163.com
License: MIT
Platform: UNKNOWN
Requires-Dist: Django (==2.2.5)
Requires-Dist: djangorestframework (==3.10.3)
Requires-Dist: Werkzeug (==0.16.0)
